pylumenta/__init__.py
pylumenta/generator.py
pylumenta-0.1.3.dist-info/LICENSE
pylumenta-0.1.3.dist-info/WHEEL
pylumenta-0.1.3.dist-info/METADATA
pylumenta-0.1.3.dist-info/RECORD
