Metadata-Version: 2.1
Name: pylumenta
Version: 0.1.3
Summary: Polumenta generator
Home-page: https://github.com/vladimirlojanica/pylumenta
Author: Vladimir Lojanica
Author-email: vladimirlojanica@gmail.com
Requires-Python: >=3.7
Classifier: License :: OSI Approved :: MIT License
Classifier: Programming Language :: Python :: 3
